pycurl.cpython-39-x86_64-linux-gnu.so
curl/__init__.py
pycurl_antitls-7.45.2.data/data/share/doc/pycurl/AUTHORS
pycurl_antitls-7.45.2.data/data/share/doc/pycurl/COPYING-LGPL
pycurl_antitls-7.45.2.data/data/share/doc/pycurl/COPYING-MIT
pycurl_antitls-7.45.2.data/data/share/doc/pycurl/ChangeLog
pycurl_antitls-7.45.2.data/data/share/doc/pycurl/INSTALL.rst
pycurl_antitls-7.45.2.data/data/share/doc/pycurl/README.rst
pycurl_antitls-7.45.2.data/data/share/doc/pycurl/RELEASE-NOTES.rst
pycurl_antitls-7.45.2.data/data/share/doc/pycurl/examples/basicfirst.py
pycurl_antitls-7.45.2.data/data/share/doc/pycurl/examples/file_upload.py
pycurl_antitls-7.45.2.data/data/share/doc/pycurl/examples/linksys.py
pycurl_antitls-7.45.2.data/data/share/doc/pycurl/examples/multi-socket_action-select.py
pycurl_antitls-7.45.2.data/data/share/doc/pycurl/examples/opensocketexception.py
pycurl_antitls-7.45.2.data/data/share/doc/pycurl/examples/retriever-multi.py
pycurl_antitls-7.45.2.data/data/share/doc/pycurl/examples/retriever.py
pycurl_antitls-7.45.2.data/data/share/doc/pycurl/examples/sfquery.py
pycurl_antitls-7.45.2.data/data/share/doc/pycurl/examples/smtp.py
pycurl_antitls-7.45.2.data/data/share/doc/pycurl/examples/ssh_keyfunction.py
pycurl_antitls-7.45.2.data/data/share/doc/pycurl/examples/xmlrpc_curl.py
pycurl_antitls-7.45.2.data/data/share/doc/pycurl/examples/quickstart/file_upload_buffer.py
pycurl_antitls-7.45.2.data/data/share/doc/pycurl/examples/quickstart/file_upload_real.py
pycurl_antitls-7.45.2.data/data/share/doc/pycurl/examples/quickstart/file_upload_real_fancy.py
pycurl_antitls-7.45.2.data/data/share/doc/pycurl/examples/quickstart/follow_redirect.py
pycurl_antitls-7.45.2.data/data/share/doc/pycurl/examples/quickstart/form_post.py
pycurl_antitls-7.45.2.data/data/share/doc/pycurl/examples/quickstart/get.py
pycurl_antitls-7.45.2.data/data/share/doc/pycurl/examples/quickstart/get_python2.py
pycurl_antitls-7.45.2.data/data/share/doc/pycurl/examples/quickstart/get_python2_https.py
pycurl_antitls-7.45.2.dist-info/AUTHORS
pycurl_antitls-7.45.2.dist-info/COPYING-LGPL
pycurl_antitls-7.45.2.dist-info/COPYING-MIT
pycurl_antitls-7.45.2.dist-info/METADATA
pycurl_antitls-7.45.2.dist-info/WHEEL
pycurl_antitls-7.45.2.dist-info/top_level.txt
pycurl_antitls-7.45.2.dist-info/RECORD
